Metadata-Version: 2.1
Name: gsender
Version: 0.0.2
Summary: 一个报警合集
Home-page: https://github.com/Leviathangk/gsender
Author: 郭一会儿
Author-email: 1015295213@qq.com
License: MIT Licence
Keywords: email,sender,dingtalk
Platform: any
